logworks/__init__.py
logworks/logworks.py
logworks-0.7.6.dist-info/METADATA
logworks-0.7.6.dist-info/RECORD
logworks-0.7.6.dist-info/WHEEL
logworks-0.7.6.dist-info/top_level.txt
test/__init__.py
test/test_logworks.py
