Metadata-Version: 2.1
Name: logworks
Version: 0.7.6
Summary: logworks is a convenience wrapper for the logging Python module.
Home-page: https://github.com/isilanes/logworks
Author: Iñaki Silanes Cristóbal
Author-email: isilanes@gmail.com
License: UNKNOWN
Keywords: logging
Platform: UNKNOWN
Classifier: Programming Language :: Python :: 3
Classifier: License :: OSI Approved :: GNU General Public License v3 (GPLv3)
Classifier: Operating System :: OS Independent
